pytest_expect_test.py
pytest_expect_test-0.1.0.dist-info/LICENSE
pytest_expect_test-0.1.0.dist-info/METADATA
pytest_expect_test-0.1.0.dist-info/WHEEL
pytest_expect_test-0.1.0.dist-info/entry_points.txt
pytest_expect_test-0.1.0.dist-info/top_level.txt
pytest_expect_test-0.1.0.dist-info/RECORD
